developer_tools/__init__.py
developer_tools-1.0.8.dist-info/LICENSE
developer_tools-1.0.8.dist-info/METADATA
developer_tools-1.0.8.dist-info/WHEEL
developer_tools-1.0.8.dist-info/entry_points.txt
developer_tools-1.0.8.dist-info/top_level.txt
developer_tools-1.0.8.dist-info/RECORD
