Metadata-Version: 2.1
Name: developer-tools
Version: 1.0.8
Summary: Useful tools for Python developers
Home-page: https://github.com/maxzheng/developer-tools
Author: Max Zheng
Author-email: maxzheng.os@gmail.com
License: MIT
Keywords: autopip entry points example installation group
Platform: UNKNOWN
Classifier: Development Status :: 5 - Production/Stable
Classifier: Intended Audience :: Developers
Classifier: Topic :: Software Development
Classifier: License :: OSI Approved :: MIT License
Classifier: Programming Language :: Python :: 3
Classifier: Programming Language :: Python :: 3.6
Requires-Python: >=3.6
